Workbook

Sheet Portfolio Tracker
A1: Programme Portfolio – RAG Status Tracker
A2: Bajaj Finserv | CoE & Technology Project Management Office — Reporting period FY2026-27 Q1 | As of 31 May 2026
A4: Programme Code | B4: Programme Name | C4: Business Line | D4: Executive Sponsor | E4: PMO Lead | F4: Delivery Partner | G4: Stage Gate | H4: Start Date | I4: Baseline Go-Live | J4: Forecast Go-Live | K4: % Complete | L4: Schedule RAG | M4: Budget RAG | N4: Scope RAG | O4: Overall RAG | P4: Open RAID | Q4: P1 Open | R4: Budget (₹ Cr) | S4: Actual (₹ Cr) | T4: % Budget Used | U4: Last Updated | V4: Status Commentary
A5: BFS-LND-001 | B5: Core Lending Platform Migration – Phase 2 (Commercial & SME) | C5: Lending | D5: Priya Venkat | E5: Pavan Deshpande | F5: Pennant Technologies | G5: G5 – Hypercare | H5: 45870 | I5: 46142 | J5: 46188 | K5: 0.88 | L5: Amber | M5: Amber | N5: Green | O5: =IF(OR(L5="Red",M5="Red",N5="Red"),"Red",IF(OR(L5="Amber",M5="Amber",N5="Amber"),"Amber","Green")) -> Amber | P5: =COUNTIFS('RAID Log'!$B$5:$B$36,$A5,'RAID Log'!$K$5:$K$36,"<>Closed") -> 4 | Q5: =COUNTIFS('RAID Log'!$B$5:$B$36,$A5,'RAID Log'!$J$5:$J$36,"P1",'RAID Log'!$K$5:$K$36,"<>Closed") -> 0 | R5: =SUMIFS('Budget vs Actuals'!$F$5:$F$32,'Budget vs Actuals'!$A$5:$A$32,$A5) -> 28.5 | S5: =SUMIFS('Budget vs Actuals'!$H$5:$H$32,'Budget vs Actuals'!$A$5:$A$32,$A5) -> 23.5 | T5: =IF(R5=0,0,S5/R5) -> 0.8245614 | U5: 46172 | V5: Commercial/SME ledger live; dual-run recon underway, hypercare defects trending down.
A6: BFS-AI-002 | B6: FinAI – Conversational AI for Sales (BFL 3.0) | C6: Sales / Enterprise | D6: Vivek Malhotra | E6: Sneha Iyer | F6: In-house + Nagarro | G6: G3 – Build | H6: 45962 | I6: 46295 | J6: 46295 | K6: 0.45 | L6: Green | M6: Green | N6: Green | O6: =IF(OR(L6="Red",M6="Red",N6="Red"),"Red",IF(OR(L6="Amber",M6="Amber",N6="Amber"),"Amber","Green")) -> Green | P6: =COUNTIFS('RAID Log'!$B$5:$B$36,$A6,'RAID Log'!$K$5:$K$36,"<>Closed") -> 2 | Q6: =COUNTIFS('RAID Log'!$B$5:$B$36,$A6,'RAID Log'!$J$5:$J$36,"P1",'RAID Log'!$K$5:$K$36,"<>Closed") -> 0 | R6: =SUMIFS('Budget vs Actuals'!$F$5:$F$32,'Budget vs Actuals'!$A$5:$A$32,$A6) -> 11 | S6: =SUMIFS('Budget vs Actuals'!$H$5:$H$32,'Budget vs Actuals'!$A$5:$A$32,$A6) -> 4.4 | T6: =IF(R6=0,0,S6/R6) -> 0.4 | U6: 46172 | V6: On track; guardrail design for product-claim compliance in progress.
A7: BFS-AI-003 | B7: FinAI – Explainable AI for Risk & Underwriting | C7: Risk | D7: Meera Krishnan | E7: Kavita Rao | F7: In-house | G7: G4 – Test/UAT | H7: 45915 | I7: 46234 | J7: 46265 | K7: 0.62 | L7: Amber | M7: Green | N7: Amber | O7: =IF(OR(L7="Red",M7="Red",N7="Red"),"Red",IF(OR(L7="Amber",M7="Amber",N7="Amber"),"Amber","Green")) -> Amber | P7: =COUNTIFS('RAID Log'!$B$5:$B$36,$A7,'RAID Log'!$K$5:$K$36,"<>Closed") -> 3 | Q7: =COUNTIFS('RAID Log'!$B$5:$B$36,$A7,'RAID Log'!$J$5:$J$36,"P1",'RAID Log'!$K$5:$K$36,"<>Closed") -> 1 | R7: =SUMIFS('Budget vs Actuals'!$F$5:$F$32,'Budget vs Actuals'!$A$5:$A$32,$A7) -> 7.5 | S7: =SUMIFS('Budget vs Actuals'!$H$5:$H$32,'Budget vs Actuals'!$A$5:$A$32,$A7) -> 4.5 | T7: =IF(R7=0,0,S7/R7) -> 0.6 | U7: 46172 | V7: Model interpretability for RCU sign-off is the gating item; latency tuning ongoing.
A8: BFS-AI-004 | B8: FinAI – Copilot/Autopilot in Operations & Service | C8: Operations | D8: Anil Saxena | E8: Rohan Mehta | F8: In-house + Nagarro | G8: G3 – Build | H8: 46032 | I8: 46371 | J8: 46371 | K8: 0.3 | L8: Green | M8: Amber | N8: Green | O8: =IF(OR(L8="Red",M8="Red",N8="Red"),"Red",IF(OR(L8="Amber",M8="Amber",N8="Amber"),"Amber","Green")) -> Amber | P8: =COUNTIFS('RAID Log'!$B$5:$B$36,$A8,'RAID Log'!$K$5:$K$36,"<>Closed") -> 1 | Q8: =COUNTIFS('RAID Log'!$B$5:$B$36,$A8,'RAID Log'!$J$5:$J$36,"P1",'RAID Log'!$K$5:$K$36,"<>Closed") -> 0 | R8: =SUMIFS('Budget vs Actuals'!$F$5:$F$32,'Budget vs Actuals'!$A$5:$A$32,$A8) -> 8.5 | S8: =SUMIFS('Budget vs Actuals'!$H$5:$H$32,'Budget vs Actuals'!$A$5:$A$32,$A8) -> 2.4 | T8: =IF(R8=0,0,S8/R8) -> 0.28235294 | U8: 46172 | V8: Maker-checker controls for autopilot actions under definition.
A9: BFS-CLD-005 | B9: Oracle Cloud Infrastructure Migration – Wave 2 | C9: Enterprise | D9: Rajeev Khanna | E9: Arjun Nair | F9: Oracle | G9: G3 – Build | H9: 45931 | I9: 46173 | J9: 46265 | K9: 0.55 | L9: Red | M9: Red | N9: Amber | O9: =IF(OR(L9="Red",M9="Red",N9="Red"),"Red",IF(OR(L9="Amber",M9="Amber",N9="Amber"),"Amber","Green")) -> Red | P9: =COUNTIFS('RAID Log'!$B$5:$B$36,$A9,'RAID Log'!$K$5:$K$36,"<>Closed") -> 4 | Q9: =COUNTIFS('RAID Log'!$B$5:$B$36,$A9,'RAID Log'!$J$5:$J$36,"P1",'RAID Log'!$K$5:$K$36,"<>Closed") -> 3 | R9: =SUMIFS('Budget vs Actuals'!$F$5:$F$32,'Budget vs Actuals'!$A$5:$A$32,$A9) -> 23.5 | S9: =SUMIFS('Budget vs Actuals'!$H$5:$H$32,'Budget vs Actuals'!$A$5:$A$32,$A9) -> 17.7 | T9: =IF(R9=0,0,S9/R9) -> 0.75319149 | U9: 46172 | V9: Slipped 3 months: network latency + Oracle SME ramp + cloud spend overrun. Escalated.
A10: BFS-DCX-006 | B10: Bajaj Finserv Super-App Re-platform | C10: Digital | D10: Sanjay Bhandari | E10: Sneha Iyer | F10: Nagarro | G10: G3 – Build | H10: 45992 | I10: 46326 | J10: 46356 | K10: 0.4 | L10: Amber | M10: Amber | N10: Amber | O10: =IF(OR(L10="Red",M10="Red",N10="Red"),"Red",IF(OR(L10="Amber",M10="Amber",N10="Amber"),"Amber","Green")) -> Amber | P10: =COUNTIFS('RAID Log'!$B$5:$B$36,$A10,'RAID Log'!$K$5:$K$36,"<>Closed") -> 3 | Q10: =COUNTIFS('RAID Log'!$B$5:$B$36,$A10,'RAID Log'!$J$5:$J$36,"P1",'RAID Log'!$K$5:$K$36,"<>Closed") -> 0 | R10: =SUMIFS('Budget vs Actuals'!$F$5:$F$32,'Budget vs Actuals'!$A$5:$A$32,$A10) -> 12 | S10: =SUMIFS('Budget vs Actuals'!$H$5:$H$32,'Budget vs Actuals'!$A$5:$A$32,$A10) -> 5.8 | T10: =IF(R10=0,0,S10/R10) -> 0.48333333 | U10: 46172 | V10: Front-end pod under-staffed; low-end Android performance below benchmark.
A11: BFS-CMP-007 | B11: AML Uplift – Azentio Amlock Upgrade | C11: Compliance | D11: Meera Krishnan | E11: Imran Sheikh | F11: Azentio | G11: G4 – Test/UAT | H11: 45901 | I11: 46203 | J11: 46203 | K11: 0.75 | L11: Green | M11: Green | N11: Green | O11: =IF(OR(L11="Red",M11="Red",N11="Red"),"Red",IF(OR(L11="Amber",M11="Amber",N11="Amber"),"Amber","Green")) -> Green | P11: =COUNTIFS('RAID Log'!$B$5:$B$36,$A11,'RAID Log'!$K$5:$K$36,"<>Closed") -> 2 | Q11: =COUNTIFS('RAID Log'!$B$5:$B$36,$A11,'RAID Log'!$J$5:$J$36,"P1",'RAID Log'!$K$5:$K$36,"<>Closed") -> 0 | R11: =SUMIFS('Budget vs Actuals'!$F$5:$F$32,'Budget vs Actuals'!$A$5:$A$32,$A11) -> 7 | S11: =SUMIFS('Budget vs Actuals'!$H$5:$H$32,'Budget vs Actuals'!$A$5:$A$32,$A11) -> 5.5 | T11: =IF(R11=0,0,S11/R11) -> 0.78571429 | U11: 46172 | V11: UAT progressing; false-positive tuning and FIU-IND format validation pending.
A12: BFS-GRN-008 | B12: Green Finance – Solar & EV Financing Onboarding | C12: Lending | D12: Priya Venkat | E12: Kavita Rao | F12: In-house | G12: G2 – Planning | H12: 46082 | I12: 46356 | J12: 46356 | K12: 0.18 | L12: Green | M12: Green | N12: Amber | O12: =IF(OR(L12="Red",M12="Red",N12="Red"),"Red",IF(OR(L12="Amber",M12="Amber",N12="Amber"),"Amber","Green")) -> Amber | P12: =COUNTIFS('RAID Log'!$B$5:$B$36,$A12,'RAID Log'!$K$5:$K$36,"<>Closed") -> 2 | Q12: =COUNTIFS('RAID Log'!$B$5:$B$36,$A12,'RAID Log'!$J$5:$J$36,"P1",'RAID Log'!$K$5:$K$36,"<>Closed") -> 0 | R12: =SUMIFS('Budget vs Actuals'!$F$5:$F$32,'Budget vs Actuals'!$A$5:$A$32,$A12) -> 5 | S12: =SUMIFS('Budget vs Actuals'!$H$5:$H$32,'Budget vs Actuals'!$A$5:$A$32,$A12) -> 0.4 | T12: =IF(R12=0,0,S12/R12) -> 0.08 | U12: 46172 | V12: Planning phase; partner-API discovery for asset valuation underway.
A13: BFS-DLO-009 | B13: Digital Loan Origination System Upgrade | C13: Lending | D13: Priya Venkat | E13: Pavan Deshpande | F13: In-house + Pennant | G13: G4 – Test/UAT | H13: 45945 | I13: 46218 | J13: 46249 | K13: 0.68 | L13: Amber | M13: Amber | N13: Red | O13: =IF(OR(L13="Red",M13="Red",N13="Red"),"Red",IF(OR(L13="Amber",M13="Amber",N13="Amber"),"Amber","Green")) -> Red | P13: =COUNTIFS('RAID Log'!$B$5:$B$36,$A13,'RAID Log'!$K$5:$K$36,"<>Closed") -> 4 | Q13: =COUNTIFS('RAID Log'!$B$5:$B$36,$A13,'RAID Log'!$J$5:$J$36,"P1",'RAID Log'!$K$5:$K$36,"<>Closed") -> 1 | R13: =SUMIFS('Budget vs Actuals'!$F$5:$F$32,'Budget vs Actuals'!$A$5:$A$32,$A13) -> 10 | S13: =SUMIFS('Budget vs Actuals'!$H$5:$H$32,'Budget vs Actuals'!$A$5:$A$32,$A13) -> 6.5 | T13: =IF(R13=0,0,S13/R13) -> 0.65 | U13: 46172 | V13: Scope creep (6 product variants) + RBI DLG KFS compliance gap; Pennant disbursal API pending.
A14: BFS-OBS-010 | B14: Observability Rollout – New Relic APM | C14: Enterprise | D14: Rajeev Khanna | E14: Arjun Nair | F14: New Relic | G14: G5 – Hypercare | H14: 45839 | I14: 46112 | J14: 46112 | K14: 0.95 | L14: Green | M14: Green | N14: Green | O14: =IF(OR(L14="Red",M14="Red",N14="Red"),"Red",IF(OR(L14="Amber",M14="Amber",N14="Amber"),"Amber","Green")) -> Green | P14: =COUNTIFS('RAID Log'!$B$5:$B$36,$A14,'RAID Log'!$K$5:$K$36,"<>Closed") -> 0 | Q14: =COUNTIFS('RAID Log'!$B$5:$B$36,$A14,'RAID Log'!$J$5:$J$36,"P1",'RAID Log'!$K$5:$K$36,"<>Closed") -> 0 | R14: =SUMIFS('Budget vs Actuals'!$F$5:$F$32,'Budget vs Actuals'!$A$5:$A$32,$A14) -> 4 | S14: =SUMIFS('Budget vs Actuals'!$H$5:$H$32,'Budget vs Actuals'!$A$5:$A$32,$A14) -> 3.8 | T14: =IF(R14=0,0,S14/R14) -> 0.95 | U14: 46172 | V14: Live; SLO-based alerting adopted, alert-noise issue closed.
A15: BFS-CX-011 | B15: Adobe Experience Cloud – Campaign Personalisation | C15: Marketing | D15: Sanjay Bhandari | E15: Rohan Mehta | F15: Adobe | G15: G3 – Build | H15: 45976 | I15: 46265 | J15: 46295 | K15: 0.5 | L15: Amber | M15: Green | N15: Amber | O15: =IF(OR(L15="Red",M15="Red",N15="Red"),"Red",IF(OR(L15="Amber",M15="Amber",N15="Amber"),"Amber","Green")) -> Amber | P15: =COUNTIFS('RAID Log'!$B$5:$B$36,$A15,'RAID Log'!$K$5:$K$36,"<>Closed") -> 2 | Q15: =COUNTIFS('RAID Log'!$B$5:$B$36,$A15,'RAID Log'!$J$5:$J$36,"P1",'RAID Log'!$K$5:$K$36,"<>Closed") -> 0 | R15: =SUMIFS('Budget vs Actuals'!$F$5:$F$32,'Budget vs Actuals'!$A$5:$A$32,$A15) -> 8.5 | S15: =SUMIFS('Budget vs Actuals'!$H$5:$H$32,'Budget vs Actuals'!$A$5:$A$32,$A15) -> 4.3 | T15: =IF(R15=0,0,S15/R15) -> 0.50588235 | U15: 46172 | V15: Depends on Customer 360 segments; interim use of existing CDP.
A16: BFS-DAT-012 | B16: Customer 360 Data Platform | C16: Data | D16: Vivek Malhotra | E16: Imran Sheikh | F16: In-house + Nagarro | G16: G3 – Build | H16: 45884 | I16: 46203 | J16: 46326 | K16: 0.48 | L16: Red | M16: Red | N16: Red | O16: =IF(OR(L16="Red",M16="Red",N16="Red"),"Red",IF(OR(L16="Amber",M16="Amber",N16="Amber"),"Amber","Green")) -> Red | P16: =COUNTIFS('RAID Log'!$B$5:$B$36,$A16,'RAID Log'!$K$5:$K$36,"<>Closed") -> 4 | Q16: =COUNTIFS('RAID Log'!$B$5:$B$36,$A16,'RAID Log'!$J$5:$J$36,"P1",'RAID Log'!$K$5:$K$36,"<>Closed") -> 3 | R16: =SUMIFS('Budget vs Actuals'!$F$5:$F$32,'Budget vs Actuals'!$A$5:$A$32,$A16) -> 17.5 | S16: =SUMIFS('Budget vs Actuals'!$H$5:$H$32,'Budget vs Actuals'!$A$5:$A$32,$A16) -> 9.7 | T16: =IF(R16=0,0,S16/R16) -> 0.55428571 | U16: 46172 | V16: Golden-record match 82% vs 95%; ~22% over budget; key-person risk on data architect.
A18: Illustrative training data — fictional figures and names built on publicly reported Bajaj Finserv transformation themes (Pennant pennApps migration, BFL 3.0 FinAI, OCI 2025, Customer 360). Not actual company data.

Sheet RAID Log
A1: RAID Log – Risks, Assumptions, Issues & Dependencies
A2: Bajaj Finserv | CoE & Technology Project Management Office — Reporting period FY2026-27 Q1 | As of 31 May 2026
A4: RAID ID | B4: Programme Code | C4: Type | D4: Category | E4: Description | F4: Raised Date | G4: Owner | H4: Probability | I4: Impact | J4: Priority | K4: Status | L4: Target Resolution | M4: Mitigation / Action | N4: Last Reviewed
A5: R-001 | B5: BFS-LND-001 | C5: Risk | D5: Data | E5: Reconciliation variance of 0.3% on commercial loan ledger during Phase 2 cutover | F5: 46122 | G5: Farah Khan | H5: Medium | I5: High | J5: P2 | K5: Mitigating | L5: 46183 | M5: Daily recon scripts + dual-run with legacy LMS for 2 cycles | N5: 46170
A6: R-002 | B6: BFS-LND-001 | C6: Dependency | D6: Vendor | E6: Pennant hypercare extension SOW required before legacy LMS decommission | F6: 46134 | G6: Pavan Deshpande | H6: – | I6: High | J6: P2 | K6: Open | L6: 46178 | M6: SOW under legal review; escalated to vendor management | N6: 46172
A7: R-003 | B7: BFS-LND-001 | C7: Issue | D7: Technical | E7: Batch EOD job runtime exceeds SLA window by ~40 min post-migration | F7: 46154 | G7: Sandeep Reddy | H7: – | I7: Medium | J7: P3 | K7: In Progress | L7: 46185 | M7: Query tuning + partition strategy with Pennant | N7: 46171
A8: R-004 | B8: BFS-AI-003 | C8: Risk | D8: Regulatory | E8: Explainable-AI interpretability not meeting RCU/audit threshold for adverse-action reasons | F8: 46101 | G8: Harish Bhat | H8: High | I8: High | J8: P1 | K8: Mitigating | L8: 46218 | M8: SHAP-based reason codes + model-risk sign-off with CRO office | N8: 46169
A9: R-005 | B9: BFS-AI-003 | C9: Assumption | D9: Data | E9: Assumes 24 months of clean bureau + behavioural data available for training | F9: 46068 | G9: Farah Khan | H9: – | I9: Medium | J9: P3 | K9: Open | L9: 46203 | M9: Data-quality assessment in progress | N9: 46162
A10: R-006 | B10: BFS-CLD-005 | C10: Issue | D10: Technical | E10: OCI network latency to on-prem core breaching 20ms target for synchronous calls | F10: 46117 | G10: George Mathew | H10: – | I10: High | J10: P1 | K10: In Progress | L10: 46193 | M10: FastConnect dedicated link + workload re-architecture | N10: 46172
A11: R-007 | B11: BFS-CLD-005 | C11: Risk | D11: Vendor | E11: Oracle implementation resource ramp behind plan; 3 of 8 SMEs unfilled | F11: 46109 | G11: Arjun Nair | H11: High | I11: High | J11: P1 | K11: Open | L11: 46188 | M11: Escalated to Oracle delivery exec; backfill from partner pool | N11: 46171
A12: R-008 | B12: BFS-CLD-005 | C12: Risk | D12: Financial | E12: Cloud consumption tracking ahead of budget; FinOps guardrails not yet enforced | F12: 46130 | G12: Neha Kulkarni | H12: High | I12: Medium | J12: P2 | K12: Mitigating | L12: 46203 | M12: Budget alerts + tagging policy + monthly FinOps review | N12: 46168
A13: R-009 | B13: BFS-CLD-005 | C13: Dependency | D13: Security | E13: InfoSec cloud security baseline sign-off pending before Wave 2 prod cutover | F13: 46137 | G13: Harish Bhat | H13: – | I13: High | J13: P1 | K13: Open | L13: 46213 | M13: Security review scheduled; CCM controls mapping underway | N13: 46170
A14: R-010 | B14: BFS-DAT-012 | C14: Issue | D14: Data | E14: Customer master golden-record match rate at 82% vs 95% target | F14: 46114 | G14: Farah Khan | H14: – | I14: High | J14: P1 | K14: In Progress | L14: 46234 | M14: Tuning match-merge rules + manual stewardship for top accounts | N14: 46172
A15: R-011 | B15: BFS-DAT-012 | C15: Risk | D15: Resource | E15: Single data-architect dependency creating key-person risk across DAT-012 and AI-003 | F15: 46096 | G15: Anuradha Kulkarni | H15: High | I15: High | J15: P1 | K15: Mitigating | L15: 46203 | M15: Onboard second architect; knowledge-transfer plan | N15: 46167
A16: R-012 | B16: BFS-DAT-012 | C16: Risk | D16: Financial | E16: Forecast at completion trending ~22% over budget due to extended data remediation | F16: 46132 | G16: Neha Kulkarni | H16: High | I16: High | J16: P1 | K16: Open | L16: 46188 | M16: Re-baseline + change request to steering committee | N16: 46172
... A36: R-032 | B36: BFS-DLO-009 | C36: Risk | D36: Financial | E36: Forecast at completion ~8% over budget due to scope additions | F36: 46140 | G36: Neha Kulkarni | H36: Medium | I36: Medium | J36: P2 | K36: Open | L36: 46203 | M36: Change control + budget re-forecast | N36: 46171

Sheet Resourcing
A1: Resource & Capacity Allocation
A2: Bajaj Finserv | CoE & Technology Project Management Office — Reporting period FY2026-27 Q1 | As of 31 May 2026
A4: Resource Name | B4: Role | C4: Band | D4: Base Location | E4: Employment | F4: Vendor | G4: Programme Code | H4: Programme Name | I4: Allocation % | J4: Total Alloc % (person) | K4: Period Start | L4: Period End
A5: Anuradha Kulkarni | B5: PMO Head | C5: M5 | D5: Pune | E5: Permanent | F5: – | G5: BFS-DAT-012 | H5: =IFERROR(VLOOKUP(G5,'Portfolio Tracker'!$A$5:$B$16,2,FALSE()),"") -> Customer 360 Data Platform | I5: 0.25 | J5: =SUMIF($A$5:$A$65,$A5,$I$5:$I$65) -> 0.9 | K5: 46113 | L5: 46295
A6: Anuradha Kulkarni | B6: PMO Head | C6: M5 | D6: Pune | E6: Permanent | F6: – | G6: BFS-CLD-005 | H6: =IFERROR(VLOOKUP(G6,'Portfolio Tracker'!$A$5:$B$16,2,FALSE()),"") -> Oracle Cloud Infrastructure Migration – Wave 2 | I6: 0.25 | J6: =SUMIF($A$5:$A$65,$A6,$I$5:$I$65) -> 0.9 | K6: 46113 | L6: 46295
A7: Anuradha Kulkarni | B7: PMO Head | C7: M5 | D7: Pune | E7: Permanent | F7: – | G7: BFS-LND-001 | H7: =IFERROR(VLOOKUP(G7,'Portfolio Tracker'!$A$5:$B$16,2,FALSE()),"") -> Core Lending Platform Migration – Phase 2 (Commercial & SME) | I7: 0.2 | J7: =SUMIF($A$5:$A$65,$A7,$I$5:$I$65) -> 0.9 | K7: 46113 | L7: 46295
A8: Anuradha Kulkarni | B8: PMO Head | C8: M5 | D8: Pune | E8: Permanent | F8: – | G8: BFS-AI-003 | H8: =IFERROR(VLOOKUP(G8,'Portfolio Tracker'!$A$5:$B$16,2,FALSE()),"") -> FinAI – Explainable AI for Risk & Underwriting | I8: 0.2 | J8: =SUMIF($A$5:$A$65,$A8,$I$5:$I$65) -> 0.9 | K8: 46113 | L8: 46295
A9: Pavan Deshpande | B9: Senior Project Manager | C9: M3 | D9: Pune | E9: Permanent | F9: – | G9: BFS-LND-001 | H9: =IFERROR(VLOOKUP(G9,'Portfolio Tracker'!$A$5:$B$16,2,FALSE()),"") -> Core Lending Platform Migration – Phase 2 (Commercial & SME) | I9: 0.6 | J9: =SUMIF($A$5:$A$65,$A9,$I$5:$I$65) -> 1.1 | K9: 46113 | L9: 46295
A10: Pavan Deshpande | B10: Senior Project Manager | C10: M3 | D10: Pune | E10: Permanent | F10: – | G10: BFS-DLO-009 | H10: =IFERROR(VLOOKUP(G10,'Portfolio Tracker'!$A$5:$B$16,2,FALSE()),"") -> Digital Loan Origination System Upgrade | I10: 0.5 | J10: =SUMIF($A$5:$A$65,$A10,$I$5:$I$65) -> 1.1 | K10: 46113 | L10: 46295
A11: Sneha Iyer | B11: Senior Project Manager | C11: M3 | D11: Pune | E11: Permanent | F11: – | G11: BFS-AI-002 | H11: =IFERROR(VLOOKUP(G11,'Portfolio Tracker'!$A$5:$B$16,2,FALSE()),"") -> FinAI – Conversational AI for Sales (BFL 3.0) | I11: 0.5 | J11: =SUMIF($A$5:$A$65,$A11,$I$5:$I$65) -> 1.1 | K11: 46113 | L11: 46295
A12: Sneha Iyer | B12: Senior Project Manager | C12: M3 | D12: Pune | E12: Permanent | F12: – | G12: BFS-DCX-006 | H12: =IFERROR(VLOOKUP(G12,'Portfolio Tracker'!$A$5:$B$16,2,FALSE()),"") -> Bajaj Finserv Super-App Re-platform | I12: 0.6 | J12: =SUMIF($A$5:$A$65,$A12,$I$5:$I$65) -> 1.1 | K12: 46113 | L12: 46295
A13: Kavita Rao | B13: Project Manager | C13: M2 | D13: Pune | E13: Permanent | F13: – | G13: BFS-AI-003 | H13: =IFERROR(VLOOKUP(G13,'Portfolio Tracker'!$A$5:$B$16,2,FALSE()),"") -> FinAI – Explainable AI for Risk & Underwriting | I13: 0.5 | J13: =SUMIF($A$5:$A$65,$A13,$I$5:$I$65) -> 1.1 | K13: 46113 | L13: 46295
A14: Kavita Rao | B14: Project Manager | C14: M2 | D14: Pune | E14: Permanent | F14: – | G14: BFS-GRN-008 | H14: =IFERROR(VLOOKUP(G14,'Portfolio Tracker'!$A$5:$B$16,2,FALSE()),"") -> Green Finance – Solar & EV Financing Onboarding | I14: 0.3 | J14: =SUMIF($A$5:$A$65,$A14,$I$5:$I$65) -> 1.1 | K14: 46113 | L14: 46295
A15: Kavita Rao | B15: Project Manager | C15: M2 | D15: Pune | E15: Permanent | F15: – | G15: BFS-DLO-009 | H15: =IFERROR(VLOOKUP(G15,'Portfolio Tracker'!$A$5:$B$16,2,FALSE()),"") -> Digital Loan Origination System Upgrade | I15: 0.3 | J15: =SUMIF($A$5:$A$65,$A15,$I$5:$I$65) -> 1.1 | K15: 46113 | L15: 46295
A16: Rohan Mehta | B16: Project Manager | C16: M2 | D16: Mumbai | E16: Permanent | F16: – | G16: BFS-AI-004 | H16: =IFERROR(VLOOKUP(G16,'Portfolio Tracker'!$A$5:$B$16,2,FALSE()),"") -> FinAI – Copilot/Autopilot in Operations & Service | I16: 0.5 | J16: =SUMIF($A$5:$A$65,$A16,$I$5:$I$65) -> 1 | K16: 46113 | L16: 46295
... A65: Aakash Pillai | B65: DevOps Engineer | C65: M1 | D65: Pune | E65: Vendor | F65: Nagarro | G65: BFS-CLD-005 | H65: =IFERROR(VLOOKUP(G65,'Portfolio Tracker'!$A$5:$B$16,2,FALSE()),"") -> Oracle Cloud Infrastructure Migration – Wave 2 | I65: 0.6 | J65: =SUMIF($A$5:$A$65,$A65,$I$5:$I$65) -> 1 | K65: 46113 | L65: 46295

Sheet Budget vs Actuals
A1: Budget vs Actuals – Programme & Vendor Spend (₹ Crore)
A2: Bajaj Finserv | CoE & Technology Project Management Office — Reporting period FY2026-27 Q1 | As of 31 May 2026
A4: Programme Code | B4: Programme Name | C4: Vendor / Partner | D4: Capex / Opex | E4: Cost Type | F4: Budget FY26-27 (₹ Cr) | G4: Committed PO (₹ Cr) | H4: Actual to Date (₹ Cr) | I4: Forecast at Completion (₹ Cr) | J4: Variance (₹ Cr) | K4: Variance % | L4: PO Number
A5: BFS-LND-001 | B5: =IFERROR(VLOOKUP(A5,'Portfolio Tracker'!$A$5:$B$16,2,FALSE()),"") -> Core Lending Platform Migration – Phase 2 (Commercial & SME) | C5: Pennant Technologies | D5: Capex | E5: Implementation | F5: 18 | G5: 18 | H5: 15.5 | I5: 18.5 | J5: =F5-I5 -> -0.5 | K5: =IF(F5=0,0,J5/F5) -> -0.027777778 | L5: PO-2025-0481
A6: BFS-LND-001 | B6: =IFERROR(VLOOKUP(A6,'Portfolio Tracker'!$A$5:$B$16,2,FALSE()),"") -> Core Lending Platform Migration – Phase 2 (Commercial & SME) | C6: Pennant Technologies | D6: Opex | E6: License & AMC | F6: 6 | G6: 6 | H6: 4.2 | I6: 6 | J6: =F6-I6 -> 0 | K6: =IF(F6=0,0,J6/F6) -> 0 | L6: PO-2025-0482
A7: BFS-LND-001 | B7: =IFERROR(VLOOKUP(A7,'Portfolio Tracker'!$A$5:$B$16,2,FALSE()),"") -> Core Lending Platform Migration – Phase 2 (Commercial & SME) | C7: In-house | D7: Opex | E7: Resourcing | F7: 4.5 | G7: 4.5 | H7: 3.8 | I7: 4.6 | J7: =F7-I7 -> -0.1 | K7: =IF(F7=0,0,J7/F7) -> -0.022222222 | L7: –
A8: BFS-AI-002 | B8: =IFERROR(VLOOKUP(A8,'Portfolio Tracker'!$A$5:$B$16,2,FALSE()),"") -> FinAI – Conversational AI for Sales (BFL 3.0) | C8: In-house | D8: Opex | E8: Resourcing | F8: 5 | G8: 5 | H8: 2.1 | I8: 5 | J8: =F8-I8 -> 0 | K8: =IF(F8=0,0,J8/F8) -> 0 | L8: –
A9: BFS-AI-002 | B9: =IFERROR(VLOOKUP(A9,'Portfolio Tracker'!$A$5:$B$16,2,FALSE()),"") -> FinAI – Conversational AI for Sales (BFL 3.0) | C9: Nagarro | D9: Capex | E9: Implementation | F9: 4 | G9: 3 | H9: 1.5 | I9: 4 | J9: =F9-I9 -> 0 | K9: =IF(F9=0,0,J9/F9) -> 0 | L9: PO-2025-0533
A10: BFS-AI-002 | B10: =IFERROR(VLOOKUP(A10,'Portfolio Tracker'!$A$5:$B$16,2,FALSE()),"") -> FinAI – Conversational AI for Sales (BFL 3.0) | C10: AWS | D10: Opex | E10: Cloud Consumption | F10: 2 | G10: 0 | H10: 0.8 | I10: 2 | J10: =F10-I10 -> 0 | K10: =IF(F10=0,0,J10/F10) -> 0 | L10: –
A11: BFS-AI-003 | B11: =IFERROR(VLOOKUP(A11,'Portfolio Tracker'!$A$5:$B$16,2,FALSE()),"") -> FinAI – Explainable AI for Risk & Underwriting | C11: In-house | D11: Opex | E11: Resourcing | F11: 6 | G11: 6 | H11: 3.6 | I11: 5.9 | J11: =F11-I11 -> 0.1 | K11: =IF(F11=0,0,J11/F11) -> 0.016666667 | L11: –
A12: BFS-AI-003 | B12: =IFERROR(VLOOKUP(A12,'Portfolio Tracker'!$A$5:$B$16,2,FALSE()),"") -> FinAI – Explainable AI for Risk & Underwriting | C12: AWS | D12: Opex | E12: Cloud Consumption | F12: 1.5 | G12: 0 | H12: 0.9 | I12: 1.5 | J12: =F12-I12 -> 0 | K12: =IF(F12=0,0,J12/F12) -> 0 | L12: –
A13: BFS-AI-004 | B13: =IFERROR(VLOOKUP(A13,'Portfolio Tracker'!$A$5:$B$16,2,FALSE()),"") -> FinAI – Copilot/Autopilot in Operations & Service | C13: In-house | D13: Opex | E13: Resourcing | F13: 5.5 | G13: 5.5 | H13: 1.8 | I13: 5.5 | J13: =F13-I13 -> 0 | K13: =IF(F13=0,0,J13/F13) -> 0 | L13: –
A14: BFS-AI-004 | B14: =IFERROR(VLOOKUP(A14,'Portfolio Tracker'!$A$5:$B$16,2,FALSE()),"") -> FinAI – Copilot/Autopilot in Operations & Service | C14: Nagarro | D14: Capex | E14: Implementation | F14: 3 | G14: 2 | H14: 0.6 | I14: 3.2 | J14: =F14-I14 -> -0.2 | K14: =IF(F14=0,0,J14/F14) -> -0.066666667 | L14: PO-2026-0114
A15: BFS-CLD-005 | B15: =IFERROR(VLOOKUP(A15,'Portfolio Tracker'!$A$5:$B$16,2,FALSE()),"") -> Oracle Cloud Infrastructure Migration – Wave 2 | C15: Oracle | D15: Capex | E15: Implementation | F15: 12 | G15: 12 | H15: 8.5 | I15: 15 | J15: =F15-I15 -> -3 | K15: =IF(F15=0,0,J15/F15) -> -0.25 | L15: PO-2025-0501
A16: BFS-CLD-005 | B16: =IFERROR(VLOOKUP(A16,'Portfolio Tracker'!$A$5:$B$16,2,FALSE()),"") -> Oracle Cloud Infrastructure Migration – Wave 2 | C16: Oracle | D16: Opex | E16: Cloud Consumption | F16: 8 | G16: 0 | H16: 6.8 | I16: 12 | J16: =F16-I16 -> -4 | K16: =IF(F16=0,0,J16/F16) -> -0.5 | L16: –
... A32: BFS-DAT-012 | B32: =IFERROR(VLOOKUP(A32,'Portfolio Tracker'!$A$5:$B$16,2,FALSE()),"") -> Customer 360 Data Platform | C32: AWS | D32: Opex | E32: Cloud Consumption | F32: 2.5 | G32: 0 | H32: 1.4 | I32: 2.9 | J32: =F32-I32 -> -0.4 | K32: =IF(F32=0,0,J32/F32) -> -0.16 | L32: –
B33: TOTAL — FY2026-27 portfolio | F33: =SUM(F5:F32) -> 143 | G33: =SUM(G5:G32) -> 123 | H33: =SUM(H5:H32) -> 88.5 | I33: =SUM(I5:I32) -> 156.4 | J33: =SUM(J5:J32) -> -13.4 | K33: =IF(F33=0,0,J33/F33) -> -0.093706294
A35: Capex = capital expenditure; Opex = operating expenditure. Negative variance (in brackets) = forecast over budget. Illustrative training data — not actual Bajaj Finserv figures.
